cli.py
demo.py
git_agent_langgraph.py
main.py
routes.py
setup_user.py
controllers/git_controller.py
gitagent_ai-1.0.4.dist-info/licenses/LICENSE
services/config.py
services/git_service.py
services/groq_api_service.py
services/mongodb_service.py
utils/git_commands.py
utils/input_handler.py
utils/streaming.py
gitagent_ai-1.0.4.dist-info/METADATA
gitagent_ai-1.0.4.dist-info/WHEEL
gitagent_ai-1.0.4.dist-info/entry_points.txt
gitagent_ai-1.0.4.dist-info/top_level.txt
gitagent_ai-1.0.4.dist-info/RECORD
