Metadata-Version: 2.4
Name: gitagent-ai
Version: 1.0.4
Summary: AI-powered Git assistant with persistent context management
Author-email: Vivek Kale <vivekskale03@gmail.com>
License: MIT
Project-URL: Homepage, https://github.com/your-username/gitagent
Project-URL: Bug Reports, https://github.com/your-username/gitagent/issues
Project-URL: Source, https://github.com/your-username/gitagent
Project-URL: Documentation, https://github.com/your-username/gitagent#readme
Keywords: git,ai,assistant,automation,version-control
Classifier: Development Status :: 4 - Beta
Classifier: Intended Audience :: Developers
Classifier: Topic :: Software Development :: Version Control :: Git
Classifier: Programming Language :: Python :: 3
Classifier: Programming Language :: Python :: 3.8
Classifier: Programming Language :: Python :: 3.9
Classifier: Programming Language :: Python :: 3.10
Classifier: Programming Language :: Python :: 3.11
Classifier: Programming Language :: Python :: 3.12
Classifier: Operating System :: OS Independent
Requires-Python: >=3.8
License-File: LICENSE
Requires-Dist: requests>=2.31.0
Requires-Dist: pydantic>=2.6.3
Requires-Dist: langgraph>=0.0.15
Requires-Dist: langchain-core>=0.1.27
Requires-Dist: python-dotenv>=1.0.0
Requires-Dist: pymongo>=4.6.0
Requires-Dist: click>=8.0.0
Provides-Extra: dev
Requires-Dist: twine>=4.0.0; extra == "dev"
Requires-Dist: build>=0.10.0; extra == "dev"
Requires-Dist: pytest>=7.0.0; extra == "dev"
Requires-Dist: black>=22.0.0; extra == "dev"
Requires-Dist: flake8>=5.0.0; extra == "dev"
Dynamic: license-file
